aceflow_mcp_server/__init__.py
aceflow_mcp_server/__main__.py
aceflow_mcp_server/config.py
aceflow_mcp_server/contract_tools.py
aceflow_mcp_server/data_manager.py
aceflow_mcp_server/intelligent_prompt_generator.py
aceflow_mcp_server/main.py
aceflow_mcp_server/mcp_http_server.py
aceflow_mcp_server/mcp_output_adapter.py
aceflow_mcp_server/mcp_server.py
aceflow_mcp_server/mcp_stdio_server.py
aceflow_mcp_server/prompt_generator.py
aceflow_mcp_server/prompts.py
aceflow_mcp_server/resources.py
aceflow_mcp_server/server.py
aceflow_mcp_server/tool_prompts.py
aceflow_mcp_server/tools.py
aceflow_mcp_server/unified_config.py
aceflow_mcp_server/unified_server.py
aceflow_mcp_server/unified_tools.py
aceflow_mcp_server/cli/__init__.py
aceflow_mcp_server/cli/contract.py
aceflow_mcp_server/cli/feature.py
aceflow_mcp_server/cli/init.py
aceflow_mcp_server/cli/main.py
aceflow_mcp_server/cli/mock.py
aceflow_mcp_server/contract/__init__.py
aceflow_mcp_server/contract/completion.py
aceflow_mcp_server/contract/config.py
aceflow_mcp_server/contract/filter.py
aceflow_mcp_server/contract/generator.py
aceflow_mcp_server/contract/repo.py
aceflow_mcp_server/core/__init__.py
aceflow_mcp_server/core/contract_workflow_engine.py
aceflow_mcp_server/core/project_manager.py
aceflow_mcp_server/core/template_manager.py
aceflow_mcp_server/core/workflow_engine.py
aceflow_mcp_server/mock/__init__.py
aceflow_mcp_server/mock/server.py
aceflow_mcp_server/notification/__init__.py
aceflow_mcp_server/notification/email.py
aceflow_mcp_server/workflow/__init__.py
aceflow_mcp_server/workflow/core/__init__.py
aceflow_mcp_server/workflow/core/engine.py
aceflow_mcp_server/workflow/core/state.py
aceflow_mcp_server/workflow/exporter/__init__.py
aceflow_mcp_server/workflow/exporter/exporter.py
aceflow_mcp_server/workflow/exporter/models.py
aceflow_mcp_server/workflow/gates/__init__.py
aceflow_mcp_server/workflow/mcp/__init__.py
aceflow_mcp_server/workflow/mcp/models.py
aceflow_mcp_server/workflow/mcp/tools.py
aceflow_mcp_server-3.0.2.dist-info/licenses/LICENSE
aceflow_mcp_server-3.0.2.dist-info/METADATA
aceflow_mcp_server-3.0.2.dist-info/WHEEL
aceflow_mcp_server-3.0.2.dist-info/entry_points.txt
aceflow_mcp_server-3.0.2.dist-info/top_level.txt
aceflow_mcp_server-3.0.2.dist-info/RECORD
