Metadata-Version: 2.4
Name: aceflow-mcp-server
Version: 3.0.2
Summary: AceFlow MCP Server - AI-Driven Intelligent Workflow System with Contract-First Development, Memory Management, and 25 MCP Tools (4 Contract + 21 Workflow)
Author-email: AceFlow Team <team@aceflow.dev>
Maintainer-email: AceFlow Team <team@aceflow.dev>
License: MIT
Project-URL: Homepage, https://github.com/aceflow-pateoas/aceflow-ai
Project-URL: Documentation, https://docs.aceflow.dev/mcp
Project-URL: Repository, https://github.com/aceflow-pateoas/aceflow-ai.git
Project-URL: Issues, https://github.com/aceflow-pateoas/aceflow-ai/issues
Keywords: mcp,model-context-protocol,workflow,ai-collaboration,ai-tools,dual-direction,intelligent-workflow,claude-code,cursor
Classifier: Development Status :: 4 - Beta
Classifier: Intended Audience :: Developers
Classifier: License :: OSI Approved :: MIT License
Classifier: Programming Language :: Python :: 3
Classifier: Programming Language :: Python :: 3.8
Classifier: Programming Language :: Python :: 3.9
Classifier: Programming Language :: Python :: 3.10
Classifier: Programming Language :: Python :: 3.11
Classifier: Programming Language :: Python :: 3.12
Classifier: Topic :: Software Development :: Libraries :: Python Modules
Classifier: Topic :: Software Development :: Code Generators
Classifier: Topic :: System :: Systems Administration
Classifier: Topic :: Scientific/Engineering :: Artificial Intelligence
Requires-Python: >=3.8
License-File: LICENSE
Requires-Dist: mcp>=1.0.0
Requires-Dist: pydantic>=2.0.0
Requires-Dist: click>=8.0.0
Requires-Dist: rich>=13.0.0
Requires-Dist: psutil>=5.9.0
Requires-Dist: aiofiles>=23.0.0
Requires-Dist: python-dotenv>=1.0.0
Requires-Dist: jinja2>=3.0.0
Requires-Dist: pyyaml>=6.0.0
Requires-Dist: fastapi>=0.104.0
Requires-Dist: uvicorn[standard]>=0.24.0
Requires-Dist: starlette>=0.27.0
Requires-Dist: requests>=2.28.0
Requires-Dist: python-dateutil>=2.8.0
Provides-Extra: dev
Requires-Dist: pytest>=7.0.0; extra == "dev"
Requires-Dist: pytest-cov>=4.0.0; extra == "dev"
Requires-Dist: black>=23.0.0; extra == "dev"
Requires-Dist: isort>=5.0.0; extra == "dev"
Requires-Dist: flake8>=6.0.0; extra == "dev"
Requires-Dist: mypy>=1.0.0; extra == "dev"
Provides-Extra: performance
Requires-Dist: uvloop>=0.17.0; extra == "performance"
Requires-Dist: orjson>=3.8.0; extra == "performance"
Provides-Extra: monitoring
Requires-Dist: prometheus-client>=0.16.0; extra == "monitoring"
Requires-Dist: structlog>=22.0.0; extra == "monitoring"
Provides-Extra: all
Requires-Dist: aceflow-mcp-server[dev,monitoring,performance]; extra == "all"
Dynamic: license-file
